bpforms/__init__.py
bpforms/__main__.py
bpforms/_version.py
bpforms/core.py
bpforms/genomic_viz.template.svg
bpforms/grammar.lark
bpforms/rest.py
bpforms/util.py
bpforms/alphabet/__init__.py
bpforms/alphabet/core.py
bpforms/alphabet/dna.canonical.yml
bpforms/alphabet/dna.py
bpforms/alphabet/dna.yml
bpforms/alphabet/protein.canonical.yml
bpforms/alphabet/protein.py
bpforms/alphabet/protein.yml
bpforms/alphabet/rna.canonical.yml
bpforms/alphabet/rna.py
bpforms/alphabet/rna.yml
bpforms/config/__init__.py
bpforms/config/core.default.cfg
bpforms/config/core.py
bpforms/config/core.schema.cfg
bpforms/web/alphabet.html
bpforms/web/crosslink.html
bpforms/web/index.html
bpforms/web/css/app.css
bpforms/web/js/app.js
bpforms/web/js/app_alphabet.js
bpforms/web/js/app_crosslink.js
bpforms/xlink/__init__.py
bpforms/xlink/core.py
bpforms/xlink/xlink.yml
bpforms/xlink/xlink_xlsx2yml.py
bpforms-0.0.16.dist-info/LICENSE
bpforms-0.0.16.dist-info/METADATA
bpforms-0.0.16.dist-info/WHEEL
bpforms-0.0.16.dist-info/entry_points.txt
bpforms-0.0.16.dist-info/top_level.txt
bpforms-0.0.16.dist-info/RECORD
