Metadata-Version: 2.1
Name: bpforms
Version: 0.0.16
Summary: Unambiguous representation of modified DNA, RNA, and proteins
Home-page: https://www.bpforms.org
Author: Karr Lab
Author-email: info@karrlab.org
License: MIT
Download-URL: https://github.com/KarrLab/bpforms
Keywords: DNA,RNA,protein,post-transcriptional modification,post-translational modification,proteoform,phosphorylation,methylation
Platform: UNKNOWN
Classifier: Development Status :: 3 - Alpha
Classifier: License :: OSI Approved :: MIT License
Classifier: Programming Language :: Python
Classifier: Programming Language :: Python :: 3
Classifier: Natural Language :: English
Classifier: Operating System :: OS Independent
Classifier: Topic :: Scientific/Engineering :: Bio-Informatics
Requires-Dist: attrdict
Requires-Dist: beautifulsoup4
Requires-Dist: biopython
Requires-Dist: cement (>=3.0.0)
Requires-Dist: configobj
Requires-Dist: jinja2
Requires-Dist: lark-parser (>=0.6.6)
Requires-Dist: mendeleev
Requires-Dist: openbabel (<3)
Requires-Dist: pandas
Requires-Dist: requests
Requires-Dist: requests-cache
Requires-Dist: ruamel.yaml (>=0.15)
Requires-Dist: setuptools
Requires-Dist: sqlalchemy
Requires-Dist: wc-utils[chem] (>=0.0.14)
Provides-Extra: all
Requires-Dist: capturer ; extra == 'all'
Requires-Dist: flask ; extra == 'all'
Requires-Dist: flask-restplus ; extra == 'all'
Requires-Dist: hurry.filesize ; extra == 'all'
Requires-Dist: jupyter ; extra == 'all'
Requires-Dist: lxml ; extra == 'all'
Requires-Dist: matplotlib ; extra == 'all'
Requires-Dist: mock ; extra == 'all'
Requires-Dist: numpy ; extra == 'all'
Requires-Dist: plyplus ; extra == 'all'
Requires-Dist: pronto (>=1) ; extra == 'all'
Requires-Dist: psutil ; extra == 'all'
Requires-Dist: pyjnius ; extra == 'all'
Requires-Dist: sphinx (>=1.8) ; extra == 'all'
Requires-Dist: sphinx-fontawesome ; extra == 'all'
Requires-Dist: sphinx-rtd-theme (>=0.4.2) ; extra == 'all'
Requires-Dist: sphinxcontrib-addmetahtml (>=0.1.1) ; extra == 'all'
Requires-Dist: sphinxcontrib-bibtex ; extra == 'all'
Requires-Dist: sphinxcontrib-googleanalytics (>=0.1.1) ; extra == 'all'
Requires-Dist: sphinxcontrib-spelling ; extra == 'all'
Requires-Dist: sphinxprettysearchresults ; extra == 'all'
Requires-Dist: wc-utils[protonation] (>=0.0.14) ; extra == 'all'
Provides-Extra: docs
Requires-Dist: sphinx (>=1.8) ; extra == 'docs'
Requires-Dist: sphinx-fontawesome ; extra == 'docs'
Requires-Dist: sphinx-rtd-theme (>=0.4.2) ; extra == 'docs'
Requires-Dist: sphinxcontrib-addmetahtml (>=0.1.1) ; extra == 'docs'
Requires-Dist: sphinxcontrib-bibtex ; extra == 'docs'
Requires-Dist: sphinxcontrib-googleanalytics (>=0.1.1) ; extra == 'docs'
Requires-Dist: sphinxcontrib-spelling ; extra == 'docs'
Requires-Dist: sphinxprettysearchresults ; extra == 'docs'
Provides-Extra: draw
Requires-Dist: wc-utils[protonation] (>=0.0.14) ; extra == 'draw'
Provides-Extra: onto_export
Requires-Dist: pronto (>=1) ; extra == 'onto_export'
Provides-Extra: protonation
Requires-Dist: pyjnius ; extra == 'protonation'
Requires-Dist: wc-utils[protonation] (>=0.0.14) ; extra == 'protonation'
Provides-Extra: rest_api
Requires-Dist: flask ; extra == 'rest_api'
Requires-Dist: flask-restplus ; extra == 'rest_api'
Provides-Extra: tests
Requires-Dist: capturer ; extra == 'tests'
Requires-Dist: hurry.filesize ; extra == 'tests'
Requires-Dist: jupyter ; extra == 'tests'
Requires-Dist: lxml ; extra == 'tests'
Requires-Dist: matplotlib ; extra == 'tests'
Requires-Dist: mock ; extra == 'tests'
Requires-Dist: numpy ; extra == 'tests'
Requires-Dist: plyplus ; extra == 'tests'
Requires-Dist: psutil ; extra == 'tests'
